LICENSE
MANIFEST.in
README.md
setup.py
bin/review-rot
review_rot.egg-info/PKG-INFO
review_rot.egg-info/SOURCES.txt
review_rot.egg-info/dependency_links.txt
review_rot.egg-info/requires.txt
review_rot.egg-info/top_level.txt
reviewrot/__init__.py
reviewrot/basereview.py
reviewrot/githubstack.py
reviewrot/gitlabstack.py
reviewrot/pagurestack.py
test/test.py
test/test_githubtest.yaml
test/test_gitlabtest.yaml
test/test_mock.py
test/test_paguretest.yaml