Metadata-Version: 1.0
Name: review-rot
Version: 0.0
Summary: CLI tool to list review(pull) requests from github,gitlab,pagure and gerrit
Home-page: https://github.com/nirzari/review-rot
Author: Nirzari Iyer
Author-email: niyer@redhat.com
License: GNU GENERAL PUBLIC LICENSE Version 3
Platform: UNKNOWN
